{
    "index": 0.04,
    "rvA01-start": 0.071,
    "rvA02-motivation": 0.035,
    "rvA03-faq": 0.04,
    "rvB01-overview": 0.048,
    "rvB02-framework": 0.006,
    "rvC01-markup": 0.068,
    "rvC02-linetags": 0.085,
    "rvC03-blocktags": 0.075,
    "rvC04-commands": 0.114,
    "rvC05-markup-r": 0.007,
    "rvC06-markup-i": 0.029,
    "rvC07-markup-v": 0.026,
    "rvC08-markup-t": 0.01,
    "rvC09-markup-d": 0.013,
    "rvD01-documents": 0.02,
    "rvD02-files": 0.043,
    "rvD03-folders": 0.017,
    "rvD04-setting": 0.004,
    "rvD05-docex": 0.005,
    "rvD06-reportex": 0.002,
    "rvE01-collab": 0.032,
    "rvE02-git": 0.003,
    "rvE03-ghsearch": 0.008,
    "rvE04-publicrivt": 0.01,
    "rvF01-quickref": 0.204,
    "rvF02-terms": 0.071
}