{
    "index": 0.052,
    "rvA01-start": 0.093,
    "rvA02-motivation": 0.037,
    "rvA03-docex1": 0.007,
    "rvA04-faq": 0.052,
    "rvB01-overview": 0.068,
    "rvB02-framework": 0.024,
    "rvC01-documents": 0.02,
    "rvC02-folders": 0.013,
    "rvC03-files": 0.037,
    "rvC04-report": 0.023,
    "rvD01-markup": 0.072,
    "rvD02-linetags": 0.11,
    "rvD03-blocktags": 0.088,
    "rvD04-commands": 0.125,
    "rvD05-markup-r": 0.019,
    "rvD06-markup-i": 0.028,
    "rvD07-markup-v": 0.03,
    "rvD08-markup-t": 0.006,
    "rvD09-markup-d": 0.019,
    "rvE01-collab": 0.04,
    "rvE02-publicrivt": 0.008,
    "rvE03-git": 0.003,
    "rvE04-ghsearch": 0.008,
    "rvF01-quickref": 0.261,
    "rvF02-terms": 0.055
}