{
    "index": 0.054,
    "rvA01-start": 0.064,
    "rvA02-tutor": 0.062,
    "rvA03-file": 0.005,
    "rvA04-txt": 0.007,
    "rvA05-html": 0.009,
    "rvA06-pdf": 0.014,
    "rvA07-faq": 0.023,
    "rvB01-overview": 0.061,
    "rvB02-motivation": 0.039,
    "rvB03-framework": 0.032,
    "rvC01-documents": 0.023,
    "rvC02-files": 0.027,
    "rvC03-reports": 0.024,
    "rvC04-rivtbks": 0.018,
    "rvD01-markup": 0.054,
    "rvD02-apiscope": 0.052,
    "rvD03-linetags": 0.087,
    "rvD04-blocktags": 0.047,
    "rvD05-commands": 0.084,
    "rvD06-assign": 0.031,
    "rvE01-collab": 0.163,
    "rvE02-github": 0.015,
    "rvE03-cloudstor": 0.018,
    "rvF01-aiintro": 0.014,
    "rvF02-convert": 0.013,
    "rvF03-models": 0.011,
    "rvF04-aibackgrnd": 0.022,
    "rvF05-scripts": 0.005,
    "rvG01-quickref": 0.226,
    "rvG02-terms": 0.057
}