{
    "index": 0.049,
    "rvA01-start": 0.126,
    "rvA02-motivation": 0.044,
    "rvA03-faq": 0.055,
    "rvB01-overview": 0.065,
    "rvB02-framework": 0.02,
    "rvC01-documents": 0.02,
    "rvC02-files": 0.056,
    "rvC03-folders": 0.022,
    "rvC04-setting": 0.006,
    "rvC05-docex": 0.008,
    "rvC06-reportex": 0.004,
    "rvD01-markup": 0.075,
    "rvD02-linetags": 0.137,
    "rvD03-blocktags": 0.214,
    "rvD04-commands": 0.186,
    "rvD05-markup-r": 0.057,
    "rvD06-markup-i": 0.04,
    "rvD07-markup-v": 0.031,
    "rvD08-markup-t": 0.014,
    "rvD09-markup-d": 0.028,
    "rvE01-collab": 0.071,
    "rvE02-git": 0.005,
    "rvE03-ghsearch": 0.014,
    "rvE04-publicrivt": 0.02,
    "rvF01-quickref": 0.26,
    "rvF02-terms": 0.096
}